MANIFEST.in
README.md
setup.py
linkmobile/__init__.py
linkmobile/handlers.py
linkmobile/service.py
pylinkmobile.egg-info/PKG-INFO
pylinkmobile.egg-info/SOURCES.txt
pylinkmobile.egg-info/dependency_links.txt
pylinkmobile.egg-info/top_level.txt