Metadata-Version: 1.0
Name: pylinkmobile
Version: 0.3.0
Summary: Link Mobile Solutions API wrapper
Home-page: https://github.com/funkbit/pylinkmobile
Author: Funkbit
Author-email: post@funkbit.no
License: BSD
Platform: UNKNOWN
Classifier: Development Status :: 3 - Alpha
Classifier: Intended Audience :: Developers
Classifier: License :: OSI Approved :: BSD License
Classifier: Programming Language :: Python
Classifier: Programming Language :: Python :: 2.6
Classifier: Programming Language :: Python :: 2.7
Classifier: Topic :: Software Development :: Libraries :: Python Modules
